{
  "Light": {
    "Main": {
      "value": "#0c6dff",
      "type": "color"
    },
    "Button Text": {
      "value": "#ffffff",
      "type": "color"
    },
    "Text 1": {
      "value": "#2f2f2f",
      "type": "color"
    },
    "Text 2": {
      "value": "#2f2f2f61",
      "type": "color"
    },
    "Outline": {
      "value": "#d1d1d1",
      "type": "color"
    },
    "BG": {
      "value": "#ffffff",
      "type": "color"
    },
    "Error": {
      "value": "#ff4a4a",
      "type": "color"
    },
    "fontFamilies": {
      "inter": {
        "value": "Inter",
        "type": "fontFamilies"
      }
    },
    "lineHeights": {
      "0": {
        "value": "AUTO",
        "type": "lineHeights"
      }
    },
    "fontWeights": {
      "inter-0": {
        "value": "Bold",
        "type": "fontWeights"
      }
    },
    "fontSize": {
      "0": {
        "value": "14",
        "type": "fontSizes"
      },
      "1": {
        "value": "16",
        "type": "fontSizes"
      },
      "2": {
        "value": "18",
        "type": "fontSizes"
      },
      "3": {
        "value": "24",
        "type": "fontSizes"
      }
    },
    "letterSpacing": {
      "0": {
        "value": "0%",
        "type": "letterSpacing"
      }
    },
    "paragraphSpacing": {
      "0": {
        "value": "0",
        "type": "paragraphSpacing"
      }
    },
    "Large Text Button": {
      "value": {
        "fontFamily": "{fontFamilies.inter}",
        "fontWeight": "{fontWeights.inter-0}",
        "lineHeight": "{lineHeights.0}",
        "fontSize": "{fontSize.2}",
        "letterSpacing": "{letterSpacing.0}",
        "paragraphSpacing": "{paragraphSpacing.0}",
        "paragraphIndent": "{paragraphIndent.0}",
        "textCase": "{textCase.none}",
        "textDecoration": "{textDecoration.none}"
      },
      "type": "typography"
    },
    "Medium Text Button": {
      "value": {
        "fontFamily": "{fontFamilies.inter}",
        "fontWeight": "{fontWeights.inter-0}",
        "lineHeight": "{lineHeights.0}",
        "fontSize": "{fontSize.1}",
        "letterSpacing": "{letterSpacing.0}",
        "paragraphSpacing": "{paragraphSpacing.0}",
        "paragraphIndent": "{paragraphIndent.0}",
        "textCase": "{textCase.none}",
        "textDecoration": "{textDecoration.none}"
      },
      "type": "typography"
    },
    "Small Text Button": {
      "value": {
        "fontFamily": "{fontFamilies.inter}",
        "fontWeight": "{fontWeights.inter-0}",
        "lineHeight": "{lineHeights.0}",
        "fontSize": "{fontSize.0}",
        "letterSpacing": "{letterSpacing.0}",
        "paragraphSpacing": "{paragraphSpacing.0}",
        "paragraphIndent": "{paragraphIndent.0}",
        "textCase": "{textCase.none}",
        "textDecoration": "{textDecoration.none}"
      },
      "type": "typography"
    },
    "H1": {
      "value": {
        "fontFamily": "{fontFamilies.inter}",
        "fontWeight": "{fontWeights.inter-0}",
        "lineHeight": "{lineHeights.0}",
        "fontSize": "{fontSize.3}",
        "letterSpacing": "{letterSpacing.0}",
        "paragraphSpacing": "{paragraphSpacing.0}",
        "paragraphIndent": "{paragraphIndent.0}",
        "textCase": "{textCase.none}",
        "textDecoration": "{textDecoration.none}"
      },
      "type": "typography"
    },
    "textCase": {
      "none": {
        "value": "none",
        "type": "textCase"
      }
    },
    "textDecoration": {
      "none": {
        "value": "none",
        "type": "textDecoration"
      }
    },
    "paragraphIndent": {
      "0": {
        "value": "0px",
        "type": "dimension"
      }
    }
  },
  "Dark": {
    "Main": {
      "value": "#0c6dff",
      "type": "color"
    },
    "Button Text": {
      "value": "#ffffff",
      "type": "color"
    },
    "Text 1": {
      "value": "#efefef",
      "type": "color"
    },
    "Text 2": {
      "value": "rgba(199,199,199,0.38)",
      "type": "color"
    },
    "Outline": {
      "value": "#282828",
      "type": "color"
    },
    "BG": {
      "value": "#101010",
      "type": "color"
    },
    "Error": {
      "value": "#ff4a4a",
      "type": "color"
    }
  },
  "$themes": [],
  "$metadata": {
    "tokenSetOrder": [
      "Light",
      "Dark"
    ]
  }
}